LICENSE.txt
setup.cfg
setup.py
tensorrt_dispatch/__init__.py
tensorrt_dispatch/plugin/__init__.py
tensorrt_dispatch/plugin/_autotune.py
tensorrt_dispatch/plugin/_export.py
tensorrt_dispatch/plugin/_lib.py
tensorrt_dispatch/plugin/_plugin_class.py
tensorrt_dispatch/plugin/_tensor.py
tensorrt_dispatch/plugin/_top_level.py
tensorrt_dispatch/plugin/_utils.py
tensorrt_dispatch/plugin/_validate.py
tensorrt_dispatch_cu12.egg-info/PKG-INFO
tensorrt_dispatch_cu12.egg-info/SOURCES.txt
tensorrt_dispatch_cu12.egg-info/dependency_links.txt
tensorrt_dispatch_cu12.egg-info/requires.txt
tensorrt_dispatch_cu12.egg-info/top_level.txt
tensorrt_dispatch_cu12.egg-info/zip-safe